AUTHORS.rst
CONTRIBUTING.rst
HISTORY.rst
LICENSE
MANIFEST.in
README.rst
setup.cfg
setup.py
aio_api_crawler.egg-info/PKG-INFO
aio_api_crawler.egg-info/SOURCES.txt
aio_api_crawler.egg-info/dependency_links.txt
aio_api_crawler.egg-info/not-zip-safe
aio_api_crawler.egg-info/requires.txt
aio_api_crawler.egg-info/top_level.txt
api_crawler/__init__.py
api_crawler/worker.py
api_crawler/endpoint/__init__.py
api_crawler/endpoint/base.py
api_crawler/endpoint/html_endpoint.py
api_crawler/endpoint/json_endpoint.py
api_crawler/sink/__init__.py
api_crawler/sink/base.py
api_crawler/sink/logging.py
api_crawler/sink/motor.py
api_crawler/sink/pika.py
api_crawler/sink/tortoise.py
docs/Makefile
docs/authors.rst
docs/conf.py
docs/contributing.rst
docs/history.rst
docs/index.rst
docs/installation.rst
docs/make.bat
docs/readme.rst
docs/usage.rst
tests/__init__.py
tests/test_aio_api_crawler.py