Metadata-Version: 2.1
Name: aio-api-crawler
Version: 0.1.3
Summary: Crawler to extract data from various json api or html endpoints
Home-page: https://github.com/pawnhearts/aio_api_crawler
Author: robotnaoborot
Author-email: robotnaoborot@gmail.com
License: BSD license
Keywords: aio_api_crawler
Platform: UNKNOWN
Classifier: Development Status :: 2 - Pre-Alpha
Classifier: Intended Audience :: Developers
Classifier: License :: OSI Approved :: BSD License
Classifier: Natural Language :: English
Classifier: Programming Language :: Python :: 3
Classifier: Programming Language :: Python :: 3.5
Classifier: Programming Language :: Python :: 3.6
Classifier: Programming Language :: Python :: 3.7
Classifier: Programming Language :: Python :: 3.8
Requires-Python: >=3.5
Provides-Extra: motor
Provides-Extra: tortoise
Provides-Extra: aio-pika
